{
  "appid": "56856118-8c28-4327-851e-2caea4e0659e",
  "name": "CTIS",
  "description": "Submit threat intelligence (IOCs) to a TAXII v2.1 Server",
  "publisher": "Splunk",
  "contributors": [
    {
      "name": "Ben Liew"
    }
  ],
  "type": "threat intel",
  "main_module": "ctis_connector.py",
  "app_version": "0.0.3",
  "utctime_updated": "2024-06-17T00:13:37.000000Z",
  "package_name": "soar-ctis",
  "product_name": "TAXII v2.1 Client / CTIS",
  "product_vendor": "OASIS / ASD",
  "product_version_regex": ".*",
  "min_phantom_version": "5.4.0",
  "fips_compliant": false,
  "python_version": "3",
  "latest_tested_versions": [
    "TAXII v2.1"
  ],
  "logo": "logo_splunk.svg",
  "logo_dark": "logo_splunk_dark.svg",
  "license": "Copyright (c) 2016-2024 Splunk Inc.",
  "pip_dependencies": {
    "pypi": [
      {
        "module": "taxii2-client>=2.3.0"
      },
      {
        "module": "stix2>=3.0.1"
      }
    ]
  },
  "configuration": {
    "base_url": {
      "description": "Base URL of the TAXII REST Server",
      "order": 0,
      "data_type": "string"
    },
    "username": {
      "description": "Username",
      "order": 1,
      "data_type": "string"
    },
    "password": {
      "description": "Password",
      "order": 2,
      "data_type": "password"
    }
  },
  "actions": [
    {
      "action": "test connectivity",
      "description": "Validate the asset configuration for connectivity",
      "type": "test",
      "identifier": "test_connectivity",
      "read_only": true,
      "parameters": {},
      "output": [],
      "versions": "EQ(*)"
    }
  ]
}
